ambientagi/.DS_Store
ambientagi/__init__.py
ambientagi/config/__init__.py
ambientagi/config/logger.py
ambientagi/config/settings.py
ambientagi/providers/__init__.py
ambientagi/providers/email_provider.py
ambientagi/providers/telegram_provider.py
ambientagi/providers/twitter_provider.py
ambientagi/providers/voice_provider.py
ambientagi/py.typed
ambientagi/services/__init__.py
ambientagi/services/agent_service.py
ambientagi/services/ambient_blockchain.py
ambientagi/services/ambient_browser.py
ambientagi/services/openai_agent_wrapper.py
ambientagi/services/scheduler.py
ambientagi/services/voice.py
ambientagi/services/webui_agent.py
ambientagi/swarm_models/__init__.py
ambientagi/swarm_models/ai_suite_wrapper.py
ambientagi/swarm_models/base_llm.py
ambientagi/swarm_models/base_multimodal_model.py
ambientagi/swarm_models/base_tts.py
ambientagi/swarm_models/base_ttv.py
ambientagi/swarm_models/cog_vlm.py
ambientagi/swarm_models/dalle3.py
ambientagi/swarm_models/embeddings_base.py
ambientagi/swarm_models/fuyu.py
ambientagi/swarm_models/gemini.py
ambientagi/swarm_models/gpt4_vision_api.py
ambientagi/swarm_models/huggingface.py
ambientagi/swarm_models/huggingface_pipeline.py
ambientagi/swarm_models/idefics.py
ambientagi/swarm_models/kosmos_two.py
ambientagi/swarm_models/layoutlm_document_qa.py
ambientagi/swarm_models/lite_llm_model.py
ambientagi/swarm_models/llama3_hosted.py
ambientagi/swarm_models/llama_function_caller.py
ambientagi/swarm_models/llava.py
ambientagi/swarm_models/model_router.py
ambientagi/swarm_models/model_types.py
ambientagi/swarm_models/moondream_mm.py
ambientagi/swarm_models/nougat.py
ambientagi/swarm_models/ollama_model.py
ambientagi/swarm_models/open_dalle.py
ambientagi/swarm_models/open_router.py
ambientagi/swarm_models/openai_embeddings.py
ambientagi/swarm_models/openai_function_caller.py
ambientagi/swarm_models/openai_tts.py
ambientagi/swarm_models/palm.py
ambientagi/swarm_models/popular_llms.py
ambientagi/swarm_models/qwen.py
ambientagi-0.2.12.dist-info/METADATA
ambientagi-0.2.12.dist-info/WHEEL
ambientagi-0.2.12.dist-info/entry_points.txt
ambientagi-0.2.12.dist-info/RECORD
