Metadata-Version: 2.3
Name: ambientagi
Version: 0.2.12
Summary: Your all-in-one SDK to automate multi-agent tasks
Author: ambientagi
Author-email: admin@ambientagi.com
Requires-Python: >=3.11,<4.0
Classifier: Programming Language :: Python :: 3
Classifier: Programming Language :: Python :: 3.11
Classifier: Programming Language :: Python :: 3.12
Classifier: Programming Language :: Python :: 3.13
Requires-Dist: APScheduler (>=3.11.0)
Requires-Dist: Markdown (==3.7)
Requires-Dist: boto3 (>=1.28.0,<2.0.0)
Requires-Dist: browser-use (==0.1.29)
Requires-Dist: eth-account[secure] (==0.13.7)
Requires-Dist: firecrawl-py (>=1.10.2)
Requires-Dist: gradio (==5.10.0)
Requires-Dist: json-repair
Requires-Dist: langchain-mistralai (==0.2.4)
Requires-Dist: openai (==1.66.3)
Requires-Dist: openai-agents (==0.0.4)
Requires-Dist: playwright (>=1.49.1,<2.0.0)
Requires-Dist: pydantic (>=2.0,<3.0)
Requires-Dist: pydantic-settings (>=2.7.1,<3.0.0)
Requires-Dist: pyperclip (==1.9.0)
Requires-Dist: python-dotenv (==1.0.1)
Requires-Dist: python-logging-loki (==0.3.1)
Requires-Dist: reportlab (==4.3.1)
Requires-Dist: requests (>=2.32.3,<3.0.0)
Requires-Dist: requests-oauthlib (>=2.0.0,<3.0.0)
